SerizalizatorDeserializatorLib/BaseSerializer.py
SerizalizatorDeserializatorLib/Constants.py
SerizalizatorDeserializatorLib/DictSerializer.py
SerizalizatorDeserializatorLib/JSON.py
SerizalizatorDeserializatorLib/SerializeFactory.py
SerizalizatorDeserializatorLib/XML.py
SerizalizatorDeserializatorLib/__init__.py
SerizalizatorDeserializatorLib-0.1.0.dist-info/METADATA
SerizalizatorDeserializatorLib-0.1.0.dist-info/WHEEL
SerizalizatorDeserializatorLib-0.1.0.dist-info/top_level.txt
SerizalizatorDeserializatorLib-0.1.0.dist-info/RECORD
