Metadata-Version: 2.1
Name: SerizalizatorDeserializatorLib
Version: 0.1.0
Summary: Library for class and function serialization and deserialization
Author: PavelPavlyutkin
Author-email: pashanpmrp200431@gmail.com
License: MIT
Classifier: Intended Audience :: Developers
Classifier: License :: OSI Approved :: MIT License
Classifier: Programming Language :: Python
Classifier: Programming Language :: Python :: 3
Classifier: Programming Language :: Python :: 3.6
Classifier: Programming Language :: Python :: 3.7
Classifier: Programming Language :: Python :: 3.8
Classifier: Programming Language :: Python :: 3.9
Classifier: Programming Language :: Python :: 3.10
Classifier: Operating System :: OS Independent
Requires-Dist: regex
